tocot/__init__.py
tocot/main.py
tocot/toc_builder.py
tocot-1.0.1.dist-info/entry_points.txt
tocot-1.0.1.dist-info/LICENSE
tocot-1.0.1.dist-info/WHEEL
tocot-1.0.1.dist-info/METADATA
tocot-1.0.1.dist-info/RECORD
