Metadata-Version: 2.1
Name: tocot
Version: 1.0.1
Summary: Table Of Contents wO Tsukuru
License: MIT
Author: dondakeshimo
Author-email: went.went.takkun135@gmail.com
Requires-Python: >=3.7,<4.0
Classifier: License :: OSI Approved :: MIT License
Classifier: Programming Language :: Python :: 3
Classifier: Programming Language :: Python :: 3.7
Classifier: Programming Language :: Python :: 3.8
Requires-Dist: click (>=7.1.2,<8.0.0)
